README.md
README.rst
setup.py
hitk/__init__.py
hitk/__main__.py
hitk/basic.py
hitk/common.py
hitk/constants.py
hitk/dialogs.py
hitk/dnd01.py
hitk/dnd02.py
hitk/hello.py
hitk/icon01.py
hitk/icon02.py
hitk/launcher.py
hitk.egg-info/PKG-INFO
hitk.egg-info/SOURCES.txt
hitk.egg-info/dependency_links.txt
hitk.egg-info/entry_points.txt
hitk.egg-info/requires.txt
hitk.egg-info/top_level.txt
hitk.egg-info/zip-safe
hitk/cli/__init__.py
hitk/cli/__main__.py
hitk/cli/glob2re.py
hitk/cli/localdb.py
hitk/cli/localfiles.py
hitk/cli/maildir.py
hitk/cli/mbox.py
hitk/cli/memo.py
hitk/cli/term01.py
hitk/cli/utf7.py