Metadata-Version: 1.1
Name: hitk
Version: 0.1.2
Summary: Includes python sample code using Tkinter
Home-page: https://github.com/IwaoWatanabe/hitk
Author: Iwao Watanabe
Author-email: iwaowatanabe+hitk@gmail.com
License: MIT
Platform: UNKNOWN
Classifier: Programming Language :: Python :: 2
Classifier: Programming Language :: Python :: 2.7
Classifier: Programming Language :: Python :: 3
Classifier: Programming Language :: Python :: 3.4
Classifier: Programming Language :: Python :: 3.6
Classifier: License :: OSI Approved :: MIT License
